proposals/__init__.py
proposals/constants.py
proposals/proposal.py
proposals/proposal_discord.py
proposals/proposal_monitor.py
proposals/utils.py
propshot_bot-0.0.1.dist-info/LICENSE
propshot_bot-0.0.1.dist-info/METADATA
propshot_bot-0.0.1.dist-info/WHEEL
propshot_bot-0.0.1.dist-info/top_level.txt
propshot_bot-0.0.1.dist-info/RECORD
