Metadata-Version: 2.1
Name: propshot-bot
Version: 0.0.1
Summary: a discord plugin for snapshot proposal alerts
Home-page: https://gitlab.com/fuzzylemma/pgps
Author: Kyle Tibbetts
Author-email: fuzzylemma@gmail.com
License: UNKNOWN
Platform: UNKNOWN
